amazon_q_mcp_github/__init__.py
amazon_q_mcp_github-0.1.0.dist-info/METADATA
amazon_q_mcp_github-0.1.0.dist-info/WHEEL
amazon_q_mcp_github-0.1.0.dist-info/top_level.txt
amazon_q_mcp_github-0.1.0.dist-info/RECORD
