Metadata-Version: 2.4
Name: amazon-q-mcp-github
Version: 0.1.0
Summary: Amazon Q MCP GitHub integration tool
Author-email: Your Name <you@example.com>
License: MIT
Project-URL: Homepage, https://github.com/soufElhabti/amazon-q-mcp-github
Requires-Python: >=3.7
